timeutil/__init__.py
timeutil-2.1.0.dist-info/DESCRIPTION.rst
timeutil-2.1.0.dist-info/METADATA
timeutil-2.1.0.dist-info/RECORD
timeutil-2.1.0.dist-info/WHEEL
timeutil-2.1.0.dist-info/metadata.json
timeutil-2.1.0.dist-info/top_level.txt
