Metadata-Version: 2.0
Name: timeutil
Version: 2.1.0
Summary: Utilitities to deal with time-series lists
Home-page: UNKNOWN
Author: Ronald Ilma
Author-email: UNKNOWN
License: UNKNOWN
Platform: UNKNOWN
Classifier: Intended Audience :: Science/Research
Classifier: Development Status :: 5 - Production/Stable
Classifier: License :: OSI Approved :: MIT License
Classifier: Topic :: Scientific/Engineering :: Atmospheric Science
Classifier: Programming Language :: Python :: 3
Requires-Python: >=2.7
Requires-Dist: nose
Requires-Dist: numpy
